{"/calculator.html":29,"/images/settings.png":66,"/images/close.png":66,"/calculator.js":29,"/":171,"/index.html":159,"/favicon.ico":69,"/p404.html":1,"/js/base64.js":87,"/js/rsa.js":25,"/views.html":24,"/chat.html":32,"/images/help.png":37,"/colog.dat":7876,"/liveviews.dat":18485,"/js/bbcode-config.js":37,"/js/bbcode-parser.js":37,"/liveviews.log":1,"/col":1,"/tools/aes.html":1,"/websites/calculator.html":1,"/js/utilinspect.js":7,"/images/refresh.png":2,"/livechat.dat":2629,"/livechattyp.dat":2629,"/livechatkick.dat":2660,"/livechathere.dat":2554,"/debug/halloween.html":1}